{
    "Alaska": {
        "continent": "América do Norte",
        "borders": [
            "Vladivostok",
            "Mackenzie",
            "Vancouver"
        ]
    },
    "Mackenzie": {
        "continent": "América do Norte",
        "borders": [
            "Alaska",
            "Vancouver",
            "Ottawa",
            "Groenlândia"
        ]
    },
    "Groenlândia": {
        "continent": "América do Norte",
        "borders": [
            "Mackenzie",
            "Ottawa",
            "Labrador",
            "Islândia"
        ]
    },
    "Vancouver": {
        "continent": "América do Norte",
        "borders": [
            "Alaska",
            "Mackenzie",
            "Ottawa",
            "Califórnia"
        ]
    },
    "Ottawa": {
        "continent": "América do Norte",
        "borders": [
            "Mackenzie",
            "Groenlândia",
            "Labrador",
            "Nova York",
            "Califórnia",
            "Vancouver"
        ]
    },
    "Labrador": {
        "continent": "América do Norte",
        "borders": [
            "Groenlândia",
            "Ottawa",
            "Nova York"
        ]
    },
    "Califórnia": {
        "continent": "América do Norte",
        "borders": [
            "Vancouver",
            "Ottawa",
            "Nova York",
            "México"
        ]
    },
    "Nova York": {
        "continent": "América do Norte",
        "borders": [
            "Labrador",
            "Ottawa",
            "Califórnia",
            "México"
        ]
    },
    "México": {
        "continent": "América do Norte",
        "borders": [
            "Califórnia",
            "Nova York",
            "Venezuela"
        ]
    },
    "Venezuela": {
        "continent": "América do Sul",
        "borders": [
            "México",
            "Peru",
            "Brasil"
        ]
    },
    "Peru": {
        "continent": "América do Sul",
        "borders": [
            "Venezuela",
            "Brasil",
            "Argentina"
        ]
    },
    "Brasil": {
        "continent": "América do Sul",
        "borders": [
            "Venezuela",
            "Peru",
            "Argentina",
            "Argélia"
        ]
    },
    "Argentina": {
        "continent": "América do Sul",
        "borders": [
            "Peru",
            "Brasil"
        ]
    },
    "Islândia": {
        "continent": "Europa",
        "borders": [
            "Groenlândia",
            "Inglaterra",
            "Suécia"
        ]
    },
    "Inglaterra": {
        "continent": "Europa",
        "borders": [
            "Islândia",
            "Suécia",
            "Alemanha",
            "França"
        ]
    },
    "Suécia": {
        "continent": "Europa",
        "borders": [
            "Islândia",
            "Inglaterra",
            "Alemanha",
            "Moscou"
        ]
    },
    "Alemanha": {
        "continent": "Europa",
        "borders": [
            "Inglaterra",
            "Suécia",
            "Moscou",
            "Polônia",
            "França"
        ]
    },
    "França": {
        "continent": "Europa",
        "borders": [
            "Inglaterra",
            "Alemanha",
            "Polônia",
            "Argélia"
        ]
    },
    "Polônia": {
        "continent": "Europa",
        "borders": [
            "Alemanha",
            "França",
            "Moscou",
            "Egito",
            "Oriente Médio"
        ]
    },
    "Moscou": {
        "continent": "Europa",
        "borders": [
            "Suécia",
            "Alemanha",
            "Polônia",
            "Omsk",
            "Aral",
            "Oriente Médio"
        ]
    },
    "Argélia": {
        "continent": "África",
        "borders": [
            "França",
            "Polônia",
            "Egito",
            "Sudão",
            "Congo",
            "Brasil"
        ]
    },
    "Egito": {
        "continent": "África",
        "borders": [
            "Polônia",
            "Argélia",
            "Sudão",
            "Oriente Médio"
        ]
    },
    "Congo": {
        "continent": "África",
        "borders": [
            "Argélia",
            "Sudão",
            "África do Sul"
        ]
    },
    "Sudão": {
        "continent": "África",
        "borders": [
            "Egito",
            "Argélia",
            "Congo",
            "África do Sul",
            "Madagascar",
            "Oriente Médio"
        ]
    },
    "África do Sul": {
        "continent": "África",
        "borders": [
            "Congo",
            "Sudão",
            "Madagascar"
        ]
    },
    "Madagascar": {
        "continent": "África",
        "borders": [
            "Sudão",
            "África do Sul"
        ]
    },
    "Oriente Médio": {
        "continent": "Ásia",
        "borders": [
            "Polônia",
            "Moscou",
            "Egito",
            "Sudão",
            "Aral",
            "Índia"
        ]
    },
    "Aral": {
        "continent": "Ásia",
        "borders": [
            "Moscou",
            "Oriente Médio",
            "Índia",
            "China",
            "Omsk"
        ]
    },
    "Omsk": {
        "continent": "Ásia",
        "borders": [
            "Moscou",
            "Aral",
            "China",
            "Dudinka"
        ]
    },
    "Dudinka": {
        "continent": "Ásia",
        "borders": [
            "Omsk",
            "China",
            "Mongólia",
            "Tchita",
            "Sibéria"
        ]
    },
    "Sibéria": {
        "continent": "Ásia",
        "borders": [
            "Dudinka",
            "Vladivostok",
            "Tchita"
        ]
    },
    "Vladivostok": {
        "continent": "Ásia",
        "borders": [
            "Sibéria",
            "Dudinka",
            "Mongólia",
            "Japão",
            "Alaska"
        ]
    },
    "Tchita": {
        "continent": "Ásia",
        "borders": [
            "Dudinka",
            "Sibéria",
            "Vladivostok",
            "Mongólia"
        ]
    },
    "Mongólia": {
        "continent": "Ásia",
        "borders": [
            "Dudinka",
            "Tchita",
            "Vladivostok",
            "Japão",
            "China"
        ]
    },
    "Japão": {
        "continent": "Ásia",
        "borders": [
            "Vladivostok",
            "Mongólia"
        ]
    },
    "China": {
        "continent": "Ásia",
        "borders": [
            "Aral",
            "Omsk",
            "Dudinka",
            "Mongólia",
            "Vietnã",
            "Índia"
        ]
    },
    "Índia": {
        "continent": "Ásia",
        "borders": [
            "Oriente Médio",
            "Aral",
            "China",
            "Vietnã"
        ]
    },
    "Vietnã": {
        "continent": "Ásia",
        "borders": [
            "Índia",
            "China",
            "Indonésia"
        ]
    },
    "Indonésia": {
        "continent": "Oceania",
        "borders": [
            "Vietnã",
            "Nova Guiné",
            "Austrália Oeste"
        ]
    },
    "Nova Guiné": {
        "continent": "Oceania",
        "borders": [
            "Indonésia",
            "Austrália Leste",
            "Austrália Oeste"
        ]
    },
    "Austrália Leste": {
        "continent": "Oceania",
        "borders": [
            "Nova Guiné",
            "Austrália Oeste"
        ]
    },
    "Austrália Oeste": {
        "continent": "Oceania",
        "borders": [
            "Indonésia",
            "Nova Guiné",
            "Austrália Leste"
        ]
    }
}